{
  "target": "dep_delay_min",
  "interpretation": "conditional delay minutes if the flight is delayed",
  "training_filter": "train rows where dep_delay_min > 15",
  "target_transform": "log1p during fit, expm1 during predict via TransformedTargetRegressor",
  "selected_model": "Tuned Random Forest Regressor",
  "selection_metric": "train TimeSeriesSplit MAE, lower is better",
  "train_delayed_rows": 3619,
  "test_actual_delayed_rows": 928,
  "numeric_features": [
    "dep_latitude",
    "dep_longitude",
    "dep_elevation_ft",
    "arr_latitude",
    "arr_longitude",
    "arr_elevation_ft",
    "route_distance_km",
    "notam_count_dep",
    "notam_count_arr",
    "notam_count_route",
    "notam_active_dep",
    "notam_active_arr",
    "has_restriction_arr",
    "has_runway_closure_arr",
    "notam_max_hours_dep",
    "notam_max_hours_arr",
    "flights_dep_same_hour",
    "flights_arr_same_hour",
    "route_avg_delay_7d",
    "route_avg_delay_30d",
    "route_delay_rate_7d",
    "airline_avg_delay_7d",
    "airline_avg_delay_30d",
    "airline_delay_rate_7d",
    "dep_airport_avg_delay_7d",
    "dep_airport_avg_delay_30d",
    "dep_airport_delay_rate_7d",
    "dep_hour",
    "dep_dayofweek",
    "dep_day",
    "dep_month",
    "dep_is_weekend",
    "dep_hour_sin",
    "dep_hour_cos",
    "dep_dow_sin",
    "dep_dow_cos",
    "dep_terminal_missing",
    "route_avg_delay_7d_missing",
    "route_avg_delay_30d_missing",
    "route_delay_rate_7d_missing",
    "airline_avg_delay_7d_missing",
    "airline_avg_delay_30d_missing",
    "airline_delay_rate_7d_missing",
    "dep_airport_avg_delay_7d_missing",
    "dep_airport_avg_delay_30d_missing",
    "dep_airport_delay_rate_7d_missing"
  ],
  "categorical_features": [
    "dep_iso_region",
    "dep_municipality",
    "arr_airport_type",
    "arr_iso_region",
    "arr_municipality",
    "dep_iata_grp",
    "arr_iata_grp",
    "airline_iata_grp",
    "route_grp",
    "dep_iso_country_grp",
    "arr_iso_country_grp"
  ],
  "final_metrics_actual_delayed_test_rows": {
    "model": "Tuned Random Forest Regressor",
    "stage": "final",
    "mae": 19.804989525570313,
    "median_absolute_error": 8.168780979759179,
    "rmse": 68.89478068885214,
    "r2": -0.014023425152126068
  },
  "mlflow_registered_model_name": "flight_delay_regressor",
  "mlflow_model_uri": "models:/m-0e08252ab0c14d3dba3a1f30f6b6f973",
  "mlflow_run_id": "1160ef04565144f5b564dcc616dc1962",
  "mlflow_registered_model_version": 3,
  "mlflow_registered_model_uri": "models:/flight_delay_regressor/3"
}